oarepo_model_builder_files/__init__.py
oarepo_model_builder_files/builders/__init__.py
oarepo_model_builder_files/builders/base.py
oarepo_model_builder_files/builders/parent_builder.py
oarepo_model_builder_files/builders/invenio/__init__.py
oarepo_model_builder_files/builders/invenio/invenio_files_record.py
oarepo_model_builder_files/builders/invenio/invenio_files_record_metadata.py
oarepo_model_builder_files/builders/invenio/invenio_files_record_permissions.py
oarepo_model_builder_files/builders/invenio/invenio_files_service_config_types.py
oarepo_model_builder_files/builders/invenio/templates/invenio_files_record.py.jinja2
oarepo_model_builder_files/builders/invenio/templates/invenio_files_record_metadata.py.jinja2
oarepo_model_builder_files/builders/invenio/templates/invenio_files_record_permissions.py.jinja2
oarepo_model_builder_files/builders/invenio/templates/invenio_files_service_config_types.py.jinja2
oarepo_model_builder_files/builders/invenio_parent/__init__.py
oarepo_model_builder_files/builders/invenio_parent/invenio_files_parent_record.py
oarepo_model_builder_files/builders/invenio_parent/invenio_files_parent_record_metadata.py
oarepo_model_builder_files/builders/invenio_parent/invenio_files_parent_schema.py
oarepo_model_builder_files/builders/invenio_parent/templates/invenio_files_record.py.jinja2
oarepo_model_builder_files/builders/invenio_parent/templates/invenio_files_record_metadata.py.jinja2
oarepo_model_builder_files/builders/invenio_parent/templates/invenio_files_schema.py.jinja2
oarepo_model_builder_files/builders/tests/__init__.py
oarepo_model_builder_files/builders/tests/invenio_files_conftest.py
oarepo_model_builder_files/builders/tests/invenio_files_conftest_files.py
oarepo_model_builder_files/builders/tests/invenio_files_test_file_resources.py
oarepo_model_builder_files/builders/tests/templates/invenio_files_conftest.py.jinja2
oarepo_model_builder_files/builders/tests/templates/invenio_files_conftest_files.py.jinja2
oarepo_model_builder_files-4.0.21.dist-info/METADATA
oarepo_model_builder_files-4.0.21.dist-info/WHEEL
oarepo_model_builder_files-4.0.21.dist-info/entry_points.txt
oarepo_model_builder_files-4.0.21.dist-info/top_level.txt
oarepo_model_builder_files-4.0.21.dist-info/RECORD
