Metadata-Version: 2.1
Name: oarepo-model-builder-files
Version: 4.0.21
Requires-Dist: oarepo-model-builder-tests>=4.0.0
Requires-Dist: oarepo-model-builder>=4.0.0
